{
	"cli": true,
	"target": "directory",
	"adapterName": "ctk_vis_extended",
	"title": "CTK VIS WIDGET",
	"expert": "yes",
	"features": ["adapter", "vis"],
	"adminFeatures": ["tab", "custom"],
	"type": "visualization",
	"startMode": "daemon",
	"connectionType": "local",
	"dataSource": "poll",
	"connectionIndicator": "yes",
	"language": "TypeScript",
	"nodeVersion": "14",
	"adminUi": "html",
	"tabReact": "yes",
	"tools": ["ESLint", "Prettier", "code coverage", "devcontainer"],
	"i18n": "words.js",
	"releaseScript": "yes",
	"devServer": "yes",
	"devServerPort": 8081,
	"indentation": "Tab",
	"quotes": "double",
	"es6class": "yes",
	"authorName": "HCPSMW",
	"authorGithub": "HCPSMW",
	"authorEmail": "sebastian.wien@ctk-gmbh.de",
	"gitRemoteProtocol": "HTTPS",
	"gitCommit": "yes",
	"defaultBranch": "master",
	"license": "MIT License",
	"dependabot": "yes",
	"creatorVersion": "2.3.0"
}
